love_packaging/__init__.py
love_packaging/__main__.py
love_packaging/__version__.py
love_packaging/windows_packager.py
love_packaging-0.1.1.dist-info/WHEEL
love_packaging-0.1.1.dist-info/METADATA
love_packaging-0.1.1.dist-info/licenses/LICENSE
love_packaging-0.1.1.dist-info/RECORD
