Metadata-Version: 2.1
Name: love_packaging
Version: 0.1.1
Summary: Package your lua LOVE games with Python
License: GNU General Public License v3.0
Author-email: Richard Dally <r.dally@protonmail.com>
Requires-Python: >=3.11
Requires-Dist: loguru>=0.6.0
Requires-Dist: wget>=3.2
